odoo/addons/crm_lead_vat/README.rst
odoo/addons/crm_lead_vat/__init__.py
odoo/addons/crm_lead_vat/__manifest__.py
odoo/addons/crm_lead_vat/i18n/bg.po
odoo/addons/crm_lead_vat/i18n/crm_lead_vat.pot
odoo/addons/crm_lead_vat/i18n/de.po
odoo/addons/crm_lead_vat/i18n/es.po
odoo/addons/crm_lead_vat/i18n/fr.po
odoo/addons/crm_lead_vat/i18n/hr.po
odoo/addons/crm_lead_vat/i18n/it.po
odoo/addons/crm_lead_vat/i18n/pt_BR.po
odoo/addons/crm_lead_vat/i18n/sk.po
odoo/addons/crm_lead_vat/i18n/sl.po
odoo/addons/crm_lead_vat/i18n/zh_CN.po
odoo/addons/crm_lead_vat/models/__init__.py
odoo/addons/crm_lead_vat/models/crm_lead.py
odoo/addons/crm_lead_vat/readme/CONTRIBUTORS.rst
odoo/addons/crm_lead_vat/readme/DESCRIPTION.rst
odoo/addons/crm_lead_vat/readme/USAGE.rst
odoo/addons/crm_lead_vat/static/description/icon.png
odoo/addons/crm_lead_vat/static/description/index.html
odoo/addons/crm_lead_vat/tests/__init__.py
odoo/addons/crm_lead_vat/tests/test_lead.py
odoo/addons/crm_lead_vat/views/crm_lead_views.xml
odoo13_addon_crm_lead_vat-13.0.1.0.1.dev7.dist-info/METADATA
odoo13_addon_crm_lead_vat-13.0.1.0.1.dev7.dist-info/WHEEL
odoo13_addon_crm_lead_vat-13.0.1.0.1.dev7.dist-info/top_level.txt
odoo13_addon_crm_lead_vat-13.0.1.0.1.dev7.dist-info/RECORD
